japanmap/__init__.py
japanmap/japan.json
japanmap/japan.png
japanmap/japan0.16.json
japanmap/py.typed
japanmap-0.6.0.dist-info/METADATA
japanmap-0.6.0.dist-info/WHEEL
japanmap-0.6.0.dist-info/licenses/LICENSE
japanmap-0.6.0.dist-info/RECORD
