Metadata-Version: 2.3
Name: japanmap
Version: 0.6.0
Summary: `japanmap` is a package for Japanese map.
Project-URL: homepage, https://github.com/SaitoTsutomu/japanmap
Author-email: Saito Tsutomu <tsutomu7@hotmail.co.jp>
License: Apache-2.0
License-File: LICENSE
Classifier: Development Status :: 1 - Planning
Classifier: License :: OSI Approved :: Apache Software License
Classifier: Programming Language :: Python
Classifier: Topic :: Scientific/Engineering
Classifier: Topic :: Software Development
Requires-Python: >=3.11
Requires-Dist: opencv-python>=4.10.0.84
Requires-Dist: pillow>=10.4.0
